{"book_index.md":"d3845c50","godotengine_readme.md":"3c954c65","godotengine_basics_debugger.md":"af06bb6c","godotengine_basics_func.md":"626e68d9","godotengine_basics_if.md":"5e0a53c4","godotengine_basics_lifecycle.md":"068d46ab","godotengine_basics_gdscript.md":"6f76b608","godotengine_basics_index.md":"58dc1aed","godotengine_basics_process.md":"f79118fd","godotengine_basics_setget.md":"82045493","godotengine_basics_作用域(scope).md":"b5fd24ce","godotengine_basics_信号(signals).md":"39e16091","godotengine_basics_信号.md":"76db52f5","godotengine_basics_内存管理(memorymanagement).md":"683e2908","godotengine_basics_变量variable.md":"eac27c5a","godotengine_basics_场景树.md":"116acd49","godotengine_basics_多线程.md":"93e0b39f","godotengine_basics_字典(dictionary).md":"ba3561e2","godotengine_basics_导出关键字(export).md":"2041bb07","godotengine_basics_循环依赖(cyclic dependency).md":"eafbf7e7","godotengine_basics_循环语句(loop).md":"133aa8f2","godotengine_basics_数组(array).md":"2a7c7881","godotengine_basics_枚举(enums).md":"35cdcc67","godotengine_basics_注释(comment).md":"5b2388e4","godotengine_basics_类(class).md":"60d4c3eb","godotengine_basics_类.md":"9534df29","godotengine_basics_脚本控制节点.md":"8ab963f7","godotengine_basics_节点生命周期.md":"eb756b8b","godotengine_basics_节点获取.md":"26c66407","godotengine_basics_静态函数(static functions).md":"7f16ad5f","godotengine_cb_codebase.md":"4a41c584","godotengine_dp_designpattern.md":"6681ce2f","godotengine_dp_单例模式.md":"fc445623","godotengine_dp_观察者模式.md":"b898d0e1","godotengine_project_index.md":"1b89bd8a","godotengine_project_isoland_人物对话.md":"a1a8beb8","godotengine_project_isoland_场景转换.md":"5e3a1c42","godotengine_project_isoland_物品拾取.md":"1051d36c","godotengine_project_isoland_项目介绍.md":"e8232615","index.md":"85c8432a","other_index.md":"49c5112e","other_mermaid.md":"0c741dd0","pm_index.md":"8372f5c8"}
